setup.cfg
setup.py
src/TestManagementLibrary/__init__.py
src/TestManagementLibrary/attachment.py
src/TestManagementLibrary/connection_manager.py
src/TestManagementLibrary/defect.py
src/TestManagementLibrary/query.py
src/TestManagementLibrary/rally.py
src/TestManagementLibrary/test_case.py
src/TestManagementLibrary/test_result.py
src/TestManagementLibrary/test_set.py
src/TestManagementLibrary/user.py
src/TestManagementLibrary/utils.py
src/robotframework_testmanagement.egg-info/PKG-INFO
src/robotframework_testmanagement.egg-info/SOURCES.txt
src/robotframework_testmanagement.egg-info/dependency_links.txt
src/robotframework_testmanagement.egg-info/requires.txt
src/robotframework_testmanagement.egg-info/top_level.txt