Metadata-Version: 1.1
Name: robotframework-testmanagement
Version: 0.1.12
Summary: Test management utility library for Robot Framework
Home-page: https://github.com/IlfirinPL/robotframework-testmanagement
Author: Michał Lula
Author-email: michal.lula@lingaro.com
License: UNKNOWN
Download-URL: https://github.com/IlfirinPL/robotframework-testmanagement/tarball/v0.1.12
Keywords: robotframework,rally,pyral
Platform: UNKNOWN
